editable_requirements/__init__.py
editable_requirements/cli.py
editable_requirements-0.1.0.dist-info/METADATA
editable_requirements-0.1.0.dist-info/WHEEL
editable_requirements-0.1.0.dist-info/entry_points.txt
editable_requirements-0.1.0.dist-info/RECORD
